{
  "functions": [
    {
      "name": "book_appointment",
      "description": "Book an appointment for the caller",
      "parameters": {
        "type": "object",
        "properties": {
          "date": {"type": "string", "description": "YYYY-MM-DD"},
          "time": {"type": "string", "description": "HH:MM"},
          "duration_minutes": {"type": "integer", "default": 30},
          "service": {"type": "string", "default": "general"}
        },
        "required": ["date", "time"]
      }
    }
  ]
}
